electronvolt.py
electronvolt-1.5.11.dist-info/LICENSE
electronvolt-1.5.11.dist-info/METADATA
electronvolt-1.5.11.dist-info/WHEEL
electronvolt-1.5.11.dist-info/top_level.txt
electronvolt-1.5.11.dist-info/RECORD
