Metadata-Version: 2.1
Name: electronvolt
Version: 1.5.11
Summary: A physics quantity calculator with units.
Home-page: https://github.com/dw61/electronvolt
Author-email: lw7jz@virginia.edu
License: UNKNOWN
Platform: UNKNOWN
Requires-Python: >=3.6
License-File: LICENSE
